easyi2l/__init__.py
easyi2l/config.py
easyi2l/db.py
easyi2l/db_type.py
easyi2l/easyi2l.py
easyi2l/logger.py
easyi2l-0.0.9.dist-info/METADATA
easyi2l-0.0.9.dist-info/WHEEL
easyi2l-0.0.9.dist-info/licenses/LICENSE
easyi2l-0.0.9.dist-info/RECORD
