Metadata-Version: 2.4
Name: easyi2l
Version: 0.0.9
Summary: A better way to use IP2Location in Python
Project-URL: Homepage, https://github.com/ozeliurs/EasyI2L
Project-URL: Issues, https://github.com/ozeliurs/EasyI2L/issues
Author-email: Ozeliurs <ozeliurs@gmail.com>
License: MIT License
License-File: LICENSE
Classifier: License :: OSI Approved :: MIT License
Classifier: Operating System :: OS Independent
Classifier: Programming Language :: Python :: 3
Requires-Python: >=3.8
Requires-Dist: ip2location
Requires-Dist: python-dotenv
Requires-Dist: requests
Requires-Dist: tqdm
